{
    "title": "Maecenas ART Token",
    "link": "https://etherscan.io/token/0xfec0cf7fe078a500abf15f1284958f22049c2c7e",
    "description": "An open blockchain platform that democratises access to Fine Art.",
    "price": "$0.1723",
    "priceBtc": "0.00002622",
    "priceEth": "0.000568",
    "volume24h": "$1,024",
    "marketCap": "$6,767,938",
    "supply": "100,000,000",
    "priceUsd": "$0.1416",
    "holders": "1863",
    "site": "https://www.maecenas.co/",
    "reputation": "NEUTRAL",
    "contract": "0xfec0cf7fe078a500abf15f1284958f22049c2c7e",
    "decimals": "18",
    "ethBalance": "0 Ether",
    "ethValue": "$0",
    "transactions": "4981",
    "creator": "0x2236705fc1bf16bd2e3eb065f4233b5ccdbfbcfd",
    "creationTx": "0x18f5a55684dfdaa6d65a123fdc0841f2187422ac30443afbc3eede1fb62907de",
    "timestamp": 1504471004,
    "blockNumber": 4235152,
    "createDate": "2017-09-03",
    "createTime": "2017-09-03T20:36:44.000Z",
    "icoPriceUsd": "",
    "icoPriceEth": "",
    "icoPriceBtx": "",
    "symbol": "ART",
    "circulatingSupply": "39,287,162.00 ART",
    "icoStartDate": "",
    "icoEndDate": "",
    "icoTotalCap": "",
    "icoTotalRaised": "",
    "country": "",
    "email": "mailto:contact@maecenas.co",
    "blog": "https://medium.com/maecenas",
    "slack": "https://slack.maecenas.co/",
    "facebook": "https://www.facebook.com/maecenasart",
    "twitter": "https://twitter.com/maecenasart",
    "github": "https://github.com/cofoundit/cfi-maecenas",
    "telegram": "",
    "whitepaper": "https://www.maecenas.co/Maecenas-WhitePaper.pdf",
    "coinMarketCap": "maecenas",
    "coinGecko": "maecenas"
}