{
    "title": "ICON",
    "link": "https://etherscan.io/token/0xb5a5f22694352c15b00323844ad545abb2b11028",
    "description": "The ICON Network is comprised of various institutions ranging from:\nfinancial institutions, insurance companies, hospitals, universities and more.",
    "price": "$0.5885",
    "priceBtc": "0.00008958",
    "priceEth": "0.001941",
    "volume24h": "$17,672,870",
    "marketCap": "$228,018,169",
    "supply": "400,228,739.999999999999999999",
    "priceUsd": "$0.5635",
    "holders": "31373",
    "site": "https://icon.foundation/",
    "reputation": "OK",
    "contract": "0xb5a5f22694352c15b00323844ad545abb2b11028",
    "decimals": "18",
    "ethBalance": "0 Ether",
    "ethValue": "$0",
    "transactions": "297770",
    "creator": "0xe16fd9b95758fe8f3a478ef9b750a64513bf2e80",
    "creationTx": "0x882350251f87729319e447ee23e00cf264ae84e75cab25fcee986a606ced8b80",
    "timestamp": 1505209181,
    "blockNumber": 4265501,
    "createDate": "2017-09-12",
    "createTime": "2017-09-12T09:39:41.000Z",
    "icoPriceUsd": "$0.12",
    "icoPriceEth": "0.0004",
    "icoPriceBtx": "",
    "symbol": "ICX",
    "circulatingSupply": "387,431,340.00 ICX",
    "icoStartDate": "Sep 20, 2017",
    "icoEndDate": "Sep 20, 2017",
    "icoTotalCap": "150,000 ETH",
    "icoTotalRaised": "",
    "country": "South Korea",
    "email": "mailto:hello@icon.foundation",
    "blog": "https://medium.com/helloiconworld",
    "slack": "",
    "facebook": "https://www.facebook.com/helloicon",
    "twitter": "https://twitter.com/helloiconworld",
    "github": "https://github.com/theloopkr/loopchain",
    "telegram": "https://t.me/helloiconworld_official",
    "whitepaper": "http://docs.icon.foundation/ICON-Whitepaper-EN-Draft.pdf",
    "coinMarketCap": "icon",
    "coinGecko": "icon"
}