{
    "title": "Jetcoin",
    "link": "https://etherscan.io/token/0x8727c112c712c4a03371ac87a74dd6ab104af768",
    "description": "Jetcoin Institute manages the distribution process of the digital fuel, Jetcoin (JET), via Jetcoin Contracts and proof of social engagement (P.O.S.E.)",
    "price": "$0.0315",
    "priceBtc": "0.00000479",
    "priceEth": "0.000104",
    "volume24h": "$20,328",
    "marketCap": "$214,804",
    "supply": "80,000,000",
    "priceUsd": "$0.0310",
    "holders": "284",
    "site": "https://jetcoin.io/",
    "reputation": "NEUTRAL",
    "contract": "0x8727c112c712c4a03371ac87a74dd6ab104af768",
    "decimals": "18",
    "ethBalance": "0 Ether",
    "ethValue": "$0",
    "transactions": "1770",
    "creator": "0x00062be45b5415268e5c9ab0d547472cbb38a7d4",
    "creationTx": "0x7b8d771e7ab805498e3a77be4bf370027dd3752bdec8bd30fffaf4d4eb21af0b",
    "timestamp": 1504820140,
    "blockNumber": 4249400,
    "createDate": "2017-09-07",
    "createTime": "2017-09-07T21:35:40.000Z",
    "icoPriceUsd": "",
    "icoPriceEth": "",
    "icoPriceBtx": "",
    "symbol": "JET",
    "circulatingSupply": "6,823,701.00 JET",
    "icoStartDate": "",
    "icoEndDate": "",
    "icoTotalCap": "",
    "icoTotalRaised": "",
    "country": "",
    "email": "",
    "blog": "",
    "slack": "https://jetcoininstitute.slack.com/",
    "facebook": "https://www.facebook.com/jetcoins/",
    "twitter": "https://twitter.com/jetcoins",
    "github": "",
    "telegram": "",
    "whitepaper": "",
    "coinMarketCap": "jetcoin",
    "coinGecko": "jetcoin"
}