{
    "title": "Jury.Online",
    "link": "https://etherscan.io/token/0xdb455c71c1bc2de4e80ca451184041ef32054001",
    "description": "Unique platform for secure investment in responsible ICOs.",
    "price": "$0.1294",
    "priceBtc": "0.00001970",
    "priceEth": "0.000427",
    "volume24h": "$10,674",
    "marketCap": "$1,161,564",
    "supply": "18,601,983.950707444511082496",
    "priceUsd": "$0.1164",
    "holders": "82543",
    "site": "https://jury.online/",
    "reputation": "NEUTRAL",
    "contract": "0xdb455c71c1bc2de4e80ca451184041ef32054001",
    "decimals": "18",
    "ethBalance": "0 Ether",
    "ethValue": "$0",
    "transactions": "3032",
    "creator": "0x160e529055d084add9634fe1c2059109c8ce044e",
    "creationTx": "0x18838652d10e3ac873b4a0736882e2714dd9fb106341a2054c3a093438a4a076",
    "timestamp": 1508627153,
    "blockNumber": 4404659,
    "createDate": "2017-10-21",
    "createTime": "2017-10-21T23:05:53.000Z",
    "icoPriceUsd": "$0.51",
    "icoPriceEth": "",
    "icoPriceBtx": "",
    "symbol": "JOT",
    "circulatingSupply": "8,974,909.00 JOT",
    "icoStartDate": "Feb 12, 2018",
    "icoEndDate": "Apr 30, 2018",
    "icoTotalCap": "",
    "icoTotalRaised": "",
    "country": "Estonia",
    "email": "mailto:contact@jury.online",
    "blog": "https://medium.com/@Jury.Online",
    "slack": "https://juryonline.slack.com/",
    "facebook": "https://www.facebook.com/JuryOnline-1222522414559995/",
    "twitter": "https://twitter.com/jury2beonline",
    "github": "https://github.com/juryonline",
    "telegram": "https://t.me/juryonline_community",
    "whitepaper": "https://jury.online/en/whitepaper.pdf",
    "coinMarketCap": "jury-online-token",
    "coinGecko": ""
}