{
    "title": "MobileGo",
    "link": "https://etherscan.io/token/0x40395044Ac3c0C57051906dA938B54BD6557F212",
    "description": "A dedicated token to bring eSports to everyone.",
    "price": "$0.1132",
    "priceBtc": "0.00001723",
    "priceEth": "0.000373",
    "volume24h": "$230,694",
    "marketCap": "$11,100,510",
    "supply": "100,000,000",
    "priceUsd": "$0.0979",
    "holders": "6221",
    "site": "https://mobilego.io/",
    "reputation": "NEUTRAL",
    "contract": "0x40395044Ac3c0C57051906dA938B54BD6557F212",
    "decimals": "8",
    "ethBalance": "0 Ether",
    "ethValue": "$0",
    "transactions": "46518",
    "creator": "0xed5eca2d2b341ba7eaa93273557f2b56b74f5107",
    "creationTx": "0xe49b2de179d229b504adb0db620a4d7e2072ebb9966725b792ed4d2278dbbe64",
    "timestamp": 1496577951,
    "blockNumber": 3819004,
    "createDate": "2017-06-04",
    "createTime": "2017-06-04T12:05:51.000Z",
    "icoPriceUsd": "$0.76",
    "icoPriceEth": "",
    "icoPriceBtx": "",
    "symbol": "MGO",
    "circulatingSupply": "98,028,877.00 MGO",
    "icoStartDate": "Apr 25, 2017",
    "icoEndDate": "May 25, 2017",
    "icoTotalCap": "",
    "icoTotalRaised": "$106,138,404",
    "country": "USA",
    "email": "",
    "blog": "https://mobilego.io/blog/",
    "slack": "https://gamecredits.com/slack.html",
    "facebook": "https://www.facebook.com/MobileGo-ICO-1967836613444499/",
    "twitter": "https://twitter.com/MobileGoIco",
    "github": "",
    "telegram": "https://t.me/mobilego",
    "whitepaper": "https://mobilego.io/pdf/MobileGo-Whitepaper.pdf",
    "coinMarketCap": "mobilego",
    "coinGecko": "mobilego"
}