{
    "title": "SPHTX",
    "link": "https://etherscan.io/token/0x3833dda0aeb6947b98ce454d89366cba8cc55528",
    "description": "Integrating Blockchain with Enterprise Applications.",
    "price": "$0.0808",
    "priceBtc": "0.00001230",
    "priceEth": "0.000267",
    "volume24h": "$62,987",
    "marketCap": "$15,618,940",
    "supply": "350,000,000",
    "priceUsd": "$0.0961",
    "holders": "7080",
    "site": "https://www.sophiatx.com/",
    "reputation": "NEUTRAL",
    "contract": "0x3833dda0aeb6947b98ce454d89366cba8cc55528",
    "decimals": "18",
    "ethBalance": "0 Ether",
    "ethValue": "$0",
    "transactions": "33008",
    "creator": "0x54b7dbbf19d4b907738a7f235919d03d7aa86d5a",
    "creationTx": "0x9fd46433b62adcf5da495ac14710455bbe2d0412ec89c99fd1857613c956924b",
    "timestamp": 1513692135,
    "blockNumber": 4760308,
    "createDate": "2017-12-19",
    "createTime": "2017-12-19T14:02:15.000Z",
    "icoPriceUsd": "$0.29",
    "icoPriceEth": "0.00062789",
    "icoPriceBtx": "",
    "symbol": "SPHTX",
    "circulatingSupply": "193,230,567.00 SPHTX",
    "icoStartDate": "Dec 07, 2017",
    "icoEndDate": "Dec 17, 2017",
    "icoTotalCap": "",
    "icoTotalRaised": "$23,470,356",
    "country": "Switzerland",
    "email": "mailto:info@sophiatx.com",
    "blog": "https://www.sophiatx.com/blog.html",
    "slack": "",
    "facebook": "https://www.facebook.com/SophiaTXC/",
    "twitter": "https://twitter.com/Sophia_TX_",
    "github": "",
    "telegram": "https://t.me/sophia_TX_com",
    "whitepaper": "https://www.sophiatx.com/_data/_custom/SophiaTX_Whitepaper.pdf",
    "coinMarketCap": "sophiatx",
    "coinGecko": "sophiatx"
}