{
    "title": "WINGS",
    "link": "https://etherscan.io/token/0x667088b212ce3d06a1b553a7221E1fD19000d9aF",
    "description": "A decentralized platform to create, join and manage projects",
    "price": "$0.1352",
    "priceBtc": "0.00002058",
    "priceEth": "0.000446",
    "volume24h": "$550,806",
    "marketCap": "$12,132,443",
    "supply": "100,000,000",
    "priceUsd": "$0.1325",
    "holders": "9155",
    "site": "https://wings.ai/",
    "reputation": "OK",
    "contract": "0x667088b212ce3d06a1b553a7221E1fD19000d9aF",
    "decimals": "18",
    "ethBalance": "0 Ether",
    "ethValue": "$0",
    "transactions": "97901",
    "creator": "0x00d5b76a4dc21e4e99e90856509da53bd0f3ec95",
    "creationTx": "0x99c5753cd08048a5ba46d8172b189ca4db7cc311861cac92896f47cc16c07cbd",
    "timestamp": 1493143729,
    "blockNumber": 3599430,
    "createDate": "2017-04-25",
    "createTime": "2017-04-25T18:08:49.000Z",
    "icoPriceUsd": "$0.028",
    "icoPriceEth": "",
    "icoPriceBtx": "",
    "symbol": "WINGS",
    "circulatingSupply": "89,708,333.00 WINGS",
    "icoStartDate": "Nov 18, 2016",
    "icoEndDate": "",
    "icoTotalCap": "",
    "icoTotalRaised": "$2,074,000",
    "country": "",
    "email": "mailto:domi@wings.ai",
    "blog": "https://blog.wings.ai/",
    "slack": "https://hi.wings.ai/",
    "facebook": "https://www.facebook.com/WingsDAO/",
    "twitter": "https://twitter.com/wingsplatform",
    "github": "",
    "telegram": "https://telegram.me/wingschat",
    "whitepaper": "https://wingsfoundation.ch/docs/WINGS_Whitepaper_V1.1.2_en.pdf",
    "coinMarketCap": "wings",
    "coinGecko": "wings"
}