{
    "BasicToken": {
        "functions": [
            "totalSupply",
            "balanceOf",
            "transfer"
        ],
        "events": [
            "Transfer"
        ]
    },
    "Destructible": {
        "functions": [
            "destroy",
            "owner",
            "transferOwnership",
            "destroyAndSend"
        ],
        "events": [
            "OwnershipTransferred"
        ]
    },
    "ERC20": {
        "functions": [
            "approve",
            "totalSupply",
            "transferFrom",
            "balanceOf",
            "transfer",
            "allowance"
        ],
        "events": [
            "Approval",
            "Transfer"
        ]
    },
    "ERC20Basic": {
        "functions": [
            "totalSupply",
            "balanceOf",
            "transfer"
        ],
        "events": [
            "Transfer"
        ]
    },
    "MintableToken": {
        "functions": [
            "mintingFinished",
            "approve",
            "totalSupply",
            "transferFrom",
            "mint",
            "decreaseApproval",
            "balanceOf",
            "finishMinting",
            "owner",
            "transfer",
            "increaseApproval",
            "allowance",
            "transferOwnership"
        ],
        "events": [
            "Mint",
            "MintFinished",
            "OwnershipTransferred",
            "Approval",
            "Transfer"
        ]
    },
    "Ownable": {
        "functions": [
            "owner",
            "transferOwnership"
        ],
        "events": [
            "OwnershipTransferred"
        ]
    },
    "Pausable": {
        "functions": [
            "unpause",
            "paused",
            "pause",
            "owner",
            "transferOwnership"
        ],
        "events": [
            "Pause",
            "Unpause",
            "OwnershipTransferred"
        ]
    },
    "PausableToken": {
        "functions": [
            "approve",
            "totalSupply",
            "transferFrom",
            "unpause",
            "paused",
            "decreaseApproval",
            "balanceOf",
            "pause",
            "owner",
            "transfer",
            "increaseApproval",
            "allowance",
            "transferOwnership"
        ],
        "events": [
            "Pause",
            "Unpause",
            "OwnershipTransferred",
            "Approval",
            "Transfer"
        ]
    },
    "SafeMath": {
        "functions": [],
        "events": []
    },
    "SaleToken": {
        "functions": [
            "mintingFinished",
            "name",
            "approve",
            "totalSupply",
            "transferFrom",
            "decimals",
            "unpause",
            "mint",
            "paused",
            "decreaseApproval",
            "balanceOf",
            "finishMinting",
            "destroy",
            "pause",
            "owner",
            "symbol",
            "transfer",
            "increaseApproval",
            "allowance",
            "transferOwnership",
            "destroyAndSend"
        ],
        "events": [
            "Mint",
            "MintFinished",
            "Pause",
            "Unpause",
            "OwnershipTransferred",
            "Approval",
            "Transfer"
        ]
    },
    "StandardToken": {
        "functions": [
            "approve",
            "totalSupply",
            "transferFrom",
            "decreaseApproval",
            "balanceOf",
            "transfer",
            "increaseApproval",
            "allowance"
        ],
        "events": [
            "Approval",
            "Transfer"
        ]
    }
}